ripozo/__init__.py
ripozo/decorators.py
ripozo/exceptions.py
ripozo/utilities.py
ripozo/dispatch/__init__.py
ripozo/dispatch/dispatch_base.py
ripozo/dispatch/adapters/__init__.py
ripozo/dispatch/adapters/base.py
ripozo/dispatch/adapters/boring_json.py
ripozo/dispatch/adapters/hal.py
ripozo/dispatch/adapters/html.py
ripozo/dispatch/adapters/siren.py
ripozo/managers/__init__.py
ripozo/managers/base.py
ripozo/viewsets/__init__.py
ripozo/viewsets/constructor.py
ripozo/viewsets/request.py
ripozo/viewsets/resource_base.py
ripozo/viewsets/constants/__init__.py
ripozo/viewsets/constants/input_categories.py
ripozo/viewsets/constants/status.py
ripozo/viewsets/fields/__init__.py
ripozo/viewsets/fields/base.py
ripozo/viewsets/fields/common.py
ripozo/viewsets/relationships/__init__.py
ripozo/viewsets/relationships/list_relationship.py
ripozo/viewsets/relationships/relationship.py
ripozo-0.1.12dev0.dist-info/DESCRIPTION.rst
ripozo-0.1.12dev0.dist-info/METADATA
ripozo-0.1.12dev0.dist-info/metadata.json
ripozo-0.1.12dev0.dist-info/RECORD
ripozo-0.1.12dev0.dist-info/top_level.txt
ripozo-0.1.12dev0.dist-info/WHEEL
