Metadata-Version: 2.0
Name: ripozo
Version: 0.1.12dev0
Summary: An tool for easily making RESTful interfaces
Home-page: UNKNOWN
Author: Tim Martin
Author-email: tim.martin@vertical-knowledge.com
License: UNKNOWN
Platform: UNKNOWN
Classifier: Development Status :: 3 - Alpha
Classifier: License :: Other/Proprietary License
Classifier: Operating System :: OS Independent
Classifier: Programming Language :: Python
Classifier: Programming Language :: Python :: 2
Classifier: Programming Language :: Python :: 2.6
Classifier: Programming Language :: Python :: 2.7
Classifier: Programming Language :: Python :: 3
Classifier: Programming Language :: Python :: 3.3
Classifier: Programming Language :: Python :: 3.4
Classifier: Programming Language :: Python :: Implementation :: PyPy
Classifier: Topic :: Software Development :: Libraries :: Python Modules
Requires-Dist: six (>=1.4.1,!=1.7.1)
Requires-Dist: jinja2
